LICENSE
MANIFEST.in
README.md
setup.cfg
setup.py
lifoid_google_translate.egg-info/PKG-INFO
lifoid_google_translate.egg-info/SOURCES.txt
lifoid_google_translate.egg-info/dependency_links.txt
lifoid_google_translate.egg-info/requires.txt
lifoid_google_translate.egg-info/top_level.txt
lifoid_googlet/__init__.py
lifoid_googlet/config.py
lifoid_googlet/translator.py
tests/__init__.py
tests/tests.py