Metadata-Version: 1.1
Name: lifoid-google-translate
Version: 0.1.0
Summary: rasa_nlu plugin for Lifoid
Home-page: https://github.com/romaryd/lifoid-google-translate
Author: Romary Dupuis
Author-email: romary@me.com
License:                                  Apache License
